setup.cfg
setup.py
./futuregrid/__init__.py
./futuregrid/cloud/__init__.py
./futuregrid/cloud/metric/FGAnalyzer.py
./futuregrid/cloud/metric/FGEucaGatherLogFiles.py
./futuregrid/cloud/metric/FGEucaMetricsDB.py
./futuregrid/cloud/metric/FGGoogleMotionChart.py
./futuregrid/cloud/metric/FGParser.py
./futuregrid/cloud/metric/FGPygooglechart.py
./futuregrid/cloud/metric/FGTemplate.py
./futuregrid/cloud/metric/FGUtility.py
./futuregrid/cloud/metric/__init__.py
futuregrid.cloud.metric.egg-info/PKG-INFO
futuregrid.cloud.metric.egg-info/SOURCES.txt
futuregrid.cloud.metric.egg-info/dependency_links.txt
futuregrid.cloud.metric.egg-info/entry_points.txt
futuregrid.cloud.metric.egg-info/top_level.txt