Metadata-Version: 1.0
Name: futuregrid.cloud.metric
Version: 2.1.5
Summary: FutureGrid: Cloud Metrics
Home-page: https://github.com/futuregrid/futuregrid-cloud-metrics
Author: Gregor von Laszewski, Hyungro Lee
Author-email: laszewski@gmail.com
License: Apache 2.0
Keywords: FutureGrid Eucalyptys Log File Analysis
Platform: UNKNOWN
